classio/__init__.py
classio/constants.py
classio/declario.py
classio-1.2.0.dist-info/LICENSE
classio-1.2.0.dist-info/METADATA
classio-1.2.0.dist-info/WHEEL
classio-1.2.0.dist-info/top_level.txt
classio-1.2.0.dist-info/RECORD
