Metadata-Version: 2.1
Name: classio
Version: 1.2.0
Summary: IO tools for python classes.
Author-email: Zach Kurtz <zkurtz@gmail.com>
Project-URL: Source, https://github.com/zkurtz/classio
Requires-Python: >=3.10
License-File: LICENSE
Requires-Dist: dummio>=1.2.0
Requires-Dist: packio>=0.0.2
